{
    "Sheet1": [
        {
            "T1_BLK_1": "x",
            "T1_OC_2": "x",
            "T3_BLK_1": "x",
            "T3_SELFC_1": "x"
        },
        {
            "T1_BLK_1": "x",
            "T1_SELFC_1": "x",
            "T1_SOC_1": "x",
            "T1_DEP_1": "x",
            "T2_BLK_1": "x",
            "T2_SELFC_1": "x",
            "T2_CON_1": "x",
            "T2_SOC_1": "x",
            "T2_RISK_3": "x",
            "T2_DEP_1": "x"
        },
        {
            "T1_BLK_1": "x",
            "T1_RISK_1": "x",
            "T1_RISK_3": "x",
            "T1_CON_2": "x",
            "T1_SELFP_1": "x",
            "T1_SOC_2": "x",
            "T2_BLK_1": "x",
            "T2_RISK_1": "x",
            "T2_SELFC_1": "x",
            "T2_SELFC_2": "x",
            "T2_BLK_3": "x",
            "T2_OC_2": "x",
            "T2_CON_2": "x",
            "T2_DEP_1": "x",
            "T2_BLK_5": "x",
            "T3_BLK_1": "x"
        },
        {
            "T1_BLK_1": "x",
            "T1_SELFC_1": "x",
            "T1_CON_1": "x",
            "T1_SOC_1": "x",
            "T1_CON_2": "x",
            "T2_BLK_1": "x",
            "T2_RISK_1": "x",
            "T2_SELFC_1": "x",
            "T2_CON_1": "x",
            "T2_SOC_1": "x",
            "T3_BLK_1": "x",
            "T3_SELFC_1": "x",
            "T3_CON_1": "x",
            "T3_SOC_1": "x",
            "T3_BLK_3": "x",
            "T3_SELFP_1": "x",
            "T3_SOC_2": "x",
            "T3_OC_3": "x"
        },
        {
            "T1_BLK_1": "x",
            "T1_SELFC_1": "x",
            "T1_SOC_1": "x",
            "T1_BLK_3": "x",
            "T1_OC_2": "x",
            "T1_CON_3": "x",
            "T2_BLK_1": "x"
        },
        {
            "T1_BLK_1": "x",
            "T1_SELFC_1": "x",
            "T1_CON_1": "x",
            "T1_BLK_3": "x",
            "T2_BLK_1": "x",
            "T2_SELFC_1": "x",
            "T2_CON_1": "x",
            "T2_BLK_3": "x",
            "T2_OC_2": "x"
        },
        {
            "T1_BLK_1": "x",
            "T1_RISK_1": "x",
            "T1_BLK_2": "x",
            "T1_SOC_1": "x",
            "T1_BLK_3": "x",
            "T1_RISK_3": "x",
            "T2_BLK_1": "x",
            "T2_RISK_1": "x",
            "T2_BLK_2": "x",
            "T2_SELFC_1": "x",
            "T2_SOC_1": "x",
            "T2_BLK_3": "x",
            "T2_OC_2": "x",
            "T2_RISK_3": "x",
            "T2_DEP_2": "x",
            "T3_BLK_1": "x",
            "T3_SELFC_1": "x",
            "T3_CON_1": "x",
            "T3_SELFC_2": "x",
            "T3_SOC_1": "x",
            "T3_BLK_3": "x",
            "T3_SELFC_3": "x",
            "T3_CON_2": "x",
            "T3_SELFP_1": "x",
            "T3_RISK_4": "x",
            "T3_DEP_2": "x"
        },
        {
            "T1_SELFC_1": "x",
            "T1_SOC_1": "x",
            "T1_CON_2": "x",
            "T1_SELFP_1": "x",
            "T3_BLK_1": "x",
            "T3_SELFC_1": "x",
            "T3_RISK_2": "x"
        },
        {
            "T2_BLK_1": "x",
            "T2_CON_1": "x",
            "T2_BLK_3": "x",
            "T2_OC_2": "x",
            "T3_BLK_1": "x",
            "T3_RISK_1": "x",
            "T3_BLK_2": "x",
            "T3_OC_1": "x",
            "T3_SELFC_1": "x",
            "T3_RISK_2": "x",
            "T3_CON_1": "x",
            "T3_SELFC_2": "x",
            "T3_SOC_1": "x",
            "T3_BLK_3": "x",
            "T3_OC_2": "x",
            "T3_RISK_3": "x",
            "T3_SELFC_3": "x",
            "T3_BLK_4": "x",
            "T3_CON_2": "x",
            "T3_SELFP_1": "x",
            "T3_SOC_2": "x",
            "T3_DEP_1": "x",
            "T3_OC_3": "x",
            "T3_CON_3": "x",
            "T3_BLK_5": "x",
            "T3_SOC_3": "x",
            "T3_DEP_2": "x"
        },
        {
            "T1_CON_1": "x",
            "T1_SOC_1": "x",
            "T1_OC_2": "x",
            "T1_SELFC_3": "x",
            "T3_BLK_1": "x",
            "T3_SELFC_1": "x",
            "T3_BLK_3": "x",
            "T3_OC_2": "x",
            "T3_RISK_3": "x",
            "T3_CON_2": "x",
            "T3_DEP_1": "x",
            "T3_CON_3": "x",
            "T3_SOC_3": "x",
            "T3_DEP_2": "x"
        },
        {
            "T1_BLK_1": "x",
            "T1_RISK_1": "x",
            "T1_BLK_2": "x",
            "T1_SELFC_1": "x",
            "T1_CON_1": "x",
            "T1_SOC_1": "x",
            "T1_CON_3": "x",
            "T2_BLK_1": "x",
            "T2_BLK_2": "x",
            "T2_OC_1": "x",
            "T2_SELFC_1": "x",
            "T2_RISK_2": "x",
            "T2_CON_1": "x",
            "T2_SOC_1": "x",
            "T2_OC_2": "x",
            "T2_CON_2": "x"
        },
        {
            "T1_BLK_1": "x",
            "T1_SELFC_1": "x",
            "T2_BLK_1": "x",
            "T2_RISK_1": "x",
            "T2_BLK_2": "x",
            "T2_SELFC_1": "x",
            "T2_CON_1": "x",
            "T2_SELFC_2": "x",
            "T2_SOC_1": "x",
            "T2_OC_2": "x",
            "T2_OC_3": "x",
            "T2_CON_3": "x",
            "T3_CON_1": "x"
        },
        {
            "T1_CON_1": "x",
            "T2_BLK_1": "x",
            "T2_CON_1": "x",
            "T2_BLK_3": "x",
            "T2_CON_2": "x",
            "T2_DEP_2": "x",
            "T3_BLK_1": "x",
            "T3_SELFC_1": "x",
            "T3_CON_1": "x",
            "T3_SOC_1": "x",
            "T3_BLK_3": "x",
            "T3_DEP_2": "x"
        },
        {
            "T1_BLK_1": "x",
            "T2_BLK_1": "x",
            "T2_BLK_3": "x"
        },
        {
            "T1_BLK_1": "x",
            "T1_RISK_1": "x",
            "T1_BLK_2": "x",
            "T1_CON_1": "x",
            "T1_SOC_1": "x",
            "T1_BLK_3": "x",
            "T1_RISK_3": "x",
            "T1_CON_2": "x",
            "T1_SELFP_1": "x",
            "T1_DEP_1": "x",
            "T1_RISK_4": "x",
            "T1_SOC_3": "x",
            "T1_DEP_2": "x",
            "T2_BLK_1": "x",
            "T2_CON_1": "x",
            "T2_SOC_1": "x",
            "T3_BLK_1": "x"
        },
        {
            "T1_BLK_1": "x",
            "T1_SELFC_1": "x",
            "T3_BLK_1": "x",
            "T3_SELFC_1": "x"
        },
        {
            "T1_BLK_1": "x",
            "T1_SELFC_1": "x",
            "T1_DEP_1": "x",
            "T3_CON_2": "x"
        },
        {
            "T1_BLK_1": "x",
            "T1_SELFC_1": "x",
            "T1_CON_1": "x",
            "T1_SOC_1": "x",
            "T1_CON_2": "x",
            "T1_CON_3": "x",
            "T1_DEP_2": "x",
            "T2_BLK_1": "x",
            "T2_RISK_1": "x",
            "T2_BLK_2": "x",
            "T2_SELFC_1": "x",
            "T2_SOC_1": "x",
            "T2_CON_2": "x",
            "T2_CON_3": "x"
        },
        {
            "T1_BLK_1": "x",
            "T1_SELFC_1": "x",
            "T2_BLK_1": "x",
            "T2_SELFC_1": "x"
        },
        {
            "T1_BLK_1": "x",
            "T1_SELFC_1": "x",
            "T1_SOC_1": "x",
            "T1_CON_2": "x",
            "T3_BLK_1": "x"
        },
        {
            "T1_BLK_1": "x",
            "T1_RISK_1": "x",
            "T1_SELFC_1": "x",
            "T1_BLK_3": "x",
            "T2_BLK_1": "x",
            "T2_SELFC_1": "x",
            "T2_SOC_1": "x",
            "T2_BLK_3": "x",
            "T3_BLK_1": "x",
            "T3_SOC_1": "x"
        },
        {
            "T1_BLK_1": "x",
            "T1_BLK_2": "x",
            "T1_SELFC_1": "x",
            "T1_SOC_1": "x",
            "T1_BLK_3": "x",
            "T1_OC_2": "x",
            "T1_RISK_3": "x",
            "T1_SELFC_3": "x",
            "T1_BLK_5": "x",
            "T3_BLK_1": "x",
            "T3_SELFC_1": "x",
            "T3_DEP_1": "x",
            "T3_OC_3": "x"
        },
        {
            "T1_CON_1": "x",
            "T1_SELFC_3": "x",
            "T2_BLK_1": "x",
            "T2_SELFC_1": "x",
            "T2_SELFC_2": "x",
            "T2_SELFC_3": "x"
        },
        {
            "T1_BLK_1": "x",
            "T1_SELFC_1": "x",
            "T1_SOC_1": "x",
            "T1_RISK_3": "x",
            "T1_CON_2": "x",
            "T1_SELFP_1": "x",
            "T1_CON_3": "x",
            "T2_BLK_1": "x",
            "T2_BLK_2": "x",
            "T2_SELFC_1": "x",
            "T2_SOC_1": "x",
            "T2_BLK_4": "x",
            "T2_CON_2": "x",
            "T2_SELFP_1": "x",
            "T2_CON_3": "x",
            "T3_BLK_1": "x",
            "T3_BLK_2": "x",
            "T3_RISK_2": "x",
            "T3_CON_1": "x",
            "T3_SOC_1": "x",
            "T3_BLK_4": "x"
        },
        {
            "T1_BLK_1": "x",
            "T1_SELFC_1": "x",
            "T1_CON_1": "x",
            "T1_SOC_1": "x",
            "T1_BLK_3": "x",
            "T1_OC_2": "x",
            "T1_RISK_3": "x",
            "T1_CON_2": "x",
            "T1_SOC_2": "x",
            "T1_CON_3": "x",
            "T1_BLK_5": "x",
            "T1_SOC_3": "x",
            "T1_DEP_2": "x",
            "T2_BLK_1": "x",
            "T2_RISK_1": "x",
            "T2_BLK_2": "x",
            "T2_OC_1": "x",
            "T2_SELFC_1": "x",
            "T2_CON_1": "x",
            "T2_SELFC_2": "x",
            "T2_SOC_1": "x",
            "T2_BLK_3": "x",
            "T2_OC_2": "x",
            "T2_RISK_3": "x",
            "T2_SELFC_3": "x",
            "T2_CON_2": "x",
            "T2_SELFP_1": "x",
            "T2_SOC_2": "x",
            "T2_DEP_1": "x",
            "T2_RISK_4": "x",
            "T2_OC_3": "x",
            "T2_CON_3": "x",
            "T2_BLK_5": "x",
            "T2_SOC_3": "x",
            "T2_DEP_2": "x"
        },
        {
            "T1_BLK_1": "x",
            "T1_RISK_1": "x",
            "T1_OC_1": "x",
            "T1_SELFC_1": "x",
            "T1_RISK_2": "x",
            "T1_CON_1": "x",
            "T1_SOC_1": "x",
            "T1_BLK_3": "x",
            "T1_RISK_3": "x",
            "T1_BLK_4": "x",
            "T1_CON_2": "x",
            "T1_SOC_2": "x",
            "T1_DEP_1": "x",
            "T1_CON_3": "x",
            "T1_SOC_3": "x",
            "T1_DEP_2": "x",
            "T2_BLK_1": "x",
            "T2_OC_2": "x",
            "T2_DEP_1": "x",
            "T3_BLK_1": "x",
            "T3_SELFC_1": "x",
            "T3_RISK_2": "x",
            "T3_CON_1": "x",
            "T3_SOC_1": "x",
            "T3_RISK_3": "x",
            "T3_SELFP_1": "x"
        },
        {
            "T1_BLK_1": "x",
            "T1_SELFC_1": "x",
            "T3_BLK_1": "x",
            "T3_RISK_1": "x",
            "T3_BLK_2": "x",
            "T3_SOC_1": "x",
            "T3_BLK_3": "x",
            "T3_CON_2": "x",
            "T3_SOC_3": "x"
        },
        {
            "T2_SOC_1": "x",
            "T2_BLK_3": "x",
            "T2_RISK_3": "x"
        },
        {
            "T1_BLK_1": "x",
            "T1_BLK_2": "x",
            "T1_CON_1": "x",
            "T1_SOC_1": "x",
            "T2_BLK_1": "x",
            "T2_RISK_1": "x",
            "T2_BLK_2": "x",
            "T2_OC_1": "x",
            "T2_SELFC_1": "x",
            "T2_CON_1": "x",
            "T2_SELFC_2": "x",
            "T2_SOC_1": "x",
            "T2_BLK_3": "x",
            "T2_RISK_3": "x",
            "T2_BLK_4": "x",
            "T2_CON_2": "x",
            "T2_SELFP_1": "x",
            "T3_SELFC_1": "x",
            "T3_SELFP_1": "x"
        },
        {
            "T2_BLK_1": "x",
            "T3_SELFC_1": "x"
        },
        {
            "T1_BLK_1": "x",
            "T1_SELFC_1": "x",
            "T1_SELFC_2": "x",
            "T3_BLK_1": "x",
            "T3_SELFC_1": "x"
        },
        {
            "T1_BLK_1": "x",
            "T1_SELFC_1": "x",
            "T1_CON_1": "x",
            "T1_SELFC_2": "x",
            "T1_SOC_1": "x",
            "T1_BLK_3": "x",
            "T1_DEP_1": "x",
            "T1_DEP_2": "x",
            "T2_BLK_1": "x"
        },
        {
            "T3_BLK_1": "x",
            "T3_SELFC_1": "x",
            "T3_SOC_1": "x"
        }
    ]
}